{"chunk_definitions":[{"row":21,"row_count":1,"visible":true,"expansion_state":0,"options":{"engine":"r","label":"setup","include":false},"document_id":"148ED697","chunk_id":"csetup_chunk","chunk_label":"setup"},{"row":67,"row_count":1,"visible":true,"expansion_state":0,"options":{"engine":"r","label":"unnamed-chunk-260"},"document_id":"148ED697","chunk_id":"cub0av275pstb","chunk_label":"unnamed-chunk-1"},{"row":83,"row_count":1,"visible":true,"expansion_state":0,"options":{"engine":"r","label":"unnamed-chunk-261"},"document_id":"148ED697","chunk_id":"cgwuv6jbo90yd","chunk_label":"unnamed-chunk-2"},{"row":87,"row_count":1,"visible":true,"expansion_state":0,"options":{"engine":"r","label":"unnamed-chunk-262"},"document_id":"148ED697","chunk_id":"cv0jd20uuqp6s","chunk_label":"unnamed-chunk-3"},{"row":90,"row_count":1,"visible":true,"expansion_state":0,"options":{"engine":"r","label":"unnamed-chunk-263"},"document_id":"148ED697","chunk_id":"c5qwin35e7o1u","chunk_label":"unnamed-chunk-4"},{"row":112,"row_count":1,"visible":true,"expansion_state":0,"options":{"engine":"r","label":"unnamed-chunk-264"},"document_id":"148ED697","chunk_id":"cmq2q0y56dzpc","chunk_label":"unnamed-chunk-5"},{"row":124,"row_count":1,"visible":true,"expansion_state":0,"options":{"engine":"r","label":"unnamed-chunk-265"},"document_id":"148ED697","chunk_id":"cef8ehfopzgnb","chunk_label":"unnamed-chunk-6"},{"row":152,"row_count":1,"visible":true,"expansion_state":0,"options":{"engine":"r","label":"unnamed-chunk-266"},"document_id":"148ED697","chunk_id":"cv5zxst8ubv4m","chunk_label":"unnamed-chunk-7"},{"row":165,"row_count":1,"visible":true,"expansion_state":0,"options":{"engine":"r","label":"unnamed-chunk-267"},"document_id":"148ED697","chunk_id":"cjzkbpl8hefji","chunk_label":"unnamed-chunk-8"},{"row":176,"row_count":1,"visible":true,"expansion_state":0,"options":{"engine":"r","label":"unnamed-chunk-268"},"document_id":"148ED697","chunk_id":"cnkf7hyvudqih","chunk_label":"unnamed-chunk-9"},{"row":185,"row_count":1,"visible":true,"expansion_state":0,"options":{"engine":"r","label":"unnamed-chunk-269"},"document_id":"148ED697","chunk_id":"cbhggu05uois5","chunk_label":"unnamed-chunk-10"},{"row":193,"row_count":1,"visible":true,"expansion_state":0,"options":{"engine":"r","label":"unnamed-chunk-270"},"document_id":"148ED697","chunk_id":"cjnbsik3kdgjo","chunk_label":"unnamed-chunk-11"},{"row":198,"row_count":1,"visible":true,"expansion_state":0,"options":{"engine":"r","label":"unnamed-chunk-271"},"document_id":"148ED697","chunk_id":"chcda1rvxo5xz","chunk_label":"unnamed-chunk-12"},{"row":210,"row_count":1,"visible":true,"expansion_state":0,"options":{"engine":"r","label":"unnamed-chunk-272"},"document_id":"148ED697","chunk_id":"c2bgc7qw3o9zs","chunk_label":"unnamed-chunk-13"},{"row":222,"row_count":1,"visible":true,"expansion_state":0,"options":{"engine":"r","label":"unnamed-chunk-273"},"document_id":"148ED697","chunk_id":"cshv7ipnweaya","chunk_label":"unnamed-chunk-14"},{"row":248,"row_count":1,"visible":true,"expansion_state":0,"options":{"engine":"r","label":"unnamed-chunk-274"},"document_id":"148ED697","chunk_id":"c0ep4ui2f5wu0","chunk_label":"unnamed-chunk-15"},{"row":259,"row_count":1,"visible":true,"expansion_state":0,"options":{"engine":"r","label":"unnamed-chunk-275"},"document_id":"148ED697","chunk_id":"ckjxctwfbe7va","chunk_label":"unnamed-chunk-16"},{"row":268,"row_count":1,"visible":true,"expansion_state":0,"options":{"engine":"r","label":"unnamed-chunk-276"},"document_id":"148ED697","chunk_id":"coqzi3451gqvp","chunk_label":"unnamed-chunk-17"},{"row":298,"row_count":1,"visible":true,"expansion_state":0,"options":{"engine":"r","label":"unnamed-chunk-277"},"document_id":"148ED697","chunk_id":"c97frnp5o9x58","chunk_label":"unnamed-chunk-18"},{"row":309,"row_count":1,"visible":true,"expansion_state":0,"options":{"engine":"r","label":"unnamed-chunk-278"},"document_id":"148ED697","chunk_id":"cd80lclv3o055","chunk_label":"unnamed-chunk-19"},{"row":318,"row_count":1,"visible":true,"expansion_state":0,"options":{"engine":"r","label":"unnamed-chunk-279"},"document_id":"148ED697","chunk_id":"cbp5xhk954m0u","chunk_label":"unnamed-chunk-20"},{"row":322,"row_count":1,"visible":true,"expansion_state":0,"options":{"engine":"r","label":"unnamed-chunk-280"},"document_id":"148ED697","chunk_id":"cvqm02obrz1ra","chunk_label":"unnamed-chunk-21"},{"row":333,"row_count":1,"visible":true,"expansion_state":0,"options":{"engine":"r","label":"unnamed-chunk-281"},"document_id":"148ED697","chunk_id":"ci5wkldf3e8ru","chunk_label":"unnamed-chunk-22"},{"row":337,"row_count":1,"visible":true,"expansion_state":0,"options":{"engine":"r","label":"unnamed-chunk-282"},"document_id":"148ED697","chunk_id":"chr6lttw1vy1p","chunk_label":"unnamed-chunk-23"},{"row":343,"row_count":1,"visible":true,"expansion_state":0,"options":{"engine":"r","label":"unnamed-chunk-283"},"document_id":"148ED697","chunk_id":"c99v4yjhctonr","chunk_label":"unnamed-chunk-24"},{"row":349,"row_count":1,"visible":true,"expansion_state":0,"options":{"engine":"r","label":"unnamed-chunk-284"},"document_id":"148ED697","chunk_id":"c2djw7spmuo6b","chunk_label":"unnamed-chunk-25"},{"row":356,"row_count":1,"visible":true,"expansion_state":0,"options":{"engine":"r","label":"unnamed-chunk-285"},"document_id":"148ED697","chunk_id":"cpf70gzkwyts2","chunk_label":"unnamed-chunk-26"},{"row":366,"row_count":1,"visible":true,"expansion_state":0,"options":{"engine":"r","label":"unnamed-chunk-286"},"document_id":"148ED697","chunk_id":"cdgfl0t7wewkz","chunk_label":"unnamed-chunk-27"},{"row":369,"row_count":1,"visible":true,"expansion_state":0,"options":{"engine":"r","label":"unnamed-chunk-287"},"document_id":"148ED697","chunk_id":"c9bbr6bo1o6wa","chunk_label":"unnamed-chunk-28"},{"row":400,"row_count":1,"visible":true,"expansion_state":0,"options":{"engine":"r","label":"unnamed-chunk-288"},"document_id":"148ED697","chunk_id":"c6qtf6v0rxaeu","chunk_label":"unnamed-chunk-29"},{"row":469,"row_count":1,"visible":true,"expansion_state":0,"options":{"engine":"r","label":"unnamed-chunk-289"},"document_id":"148ED697","chunk_id":"cu70mo5wny82v","chunk_label":"unnamed-chunk-30"},{"row":486,"row_count":1,"visible":true,"expansion_state":0,"options":{"engine":"r","label":"unnamed-chunk-290"},"document_id":"148ED697","chunk_id":"c9zsyrho46e02","chunk_label":"unnamed-chunk-31"},{"row":493,"row_count":1,"visible":true,"expansion_state":0,"options":{"engine":"r","label":"unnamed-chunk-291"},"document_id":"148ED697","chunk_id":"cbtubhomtkozm","chunk_label":"unnamed-chunk-32"},{"row":513,"row_count":1,"visible":true,"expansion_state":0,"options":{"engine":"r","label":"unnamed-chunk-292"},"document_id":"148ED697","chunk_id":"cmj2g0i4caq9n","chunk_label":"unnamed-chunk-33"},{"row":521,"row_count":1,"visible":true,"expansion_state":0,"options":{"engine":"r","label":"unnamed-chunk-293"},"document_id":"148ED697","chunk_id":"cms2r1tev5wtm","chunk_label":"unnamed-chunk-34"},{"row":531,"row_count":1,"visible":true,"expansion_state":0,"options":{"engine":"r","label":"unnamed-chunk-294"},"document_id":"148ED697","chunk_id":"czvol444fg7wq","chunk_label":"unnamed-chunk-35"},{"row":559,"row_count":1,"visible":true,"expansion_state":0,"options":{"engine":"r","label":"unnamed-chunk-295"},"document_id":"148ED697","chunk_id":"cp7nqufsvpsks","chunk_label":"unnamed-chunk-36"},{"row":581,"row_count":1,"visible":true,"expansion_state":0,"options":{"engine":"r","label":"unnamed-chunk-296"},"document_id":"148ED697","chunk_id":"chs6oh9tpdrx4","chunk_label":"unnamed-chunk-37"},{"row":592,"row_count":1,"visible":true,"expansion_state":0,"options":{"engine":"r","label":"unnamed-chunk-297"},"document_id":"148ED697","chunk_id":"c4zo399bsanfe","chunk_label":"unnamed-chunk-38"},{"row":603,"row_count":1,"visible":true,"expansion_state":0,"options":{"engine":"r","label":"unnamed-chunk-298"},"document_id":"148ED697","chunk_id":"cw1xvb6oba5yk","chunk_label":"unnamed-chunk-39"},{"row":618,"row_count":1,"visible":true,"expansion_state":0,"options":{"engine":"r","label":"unnamed-chunk-299"},"document_id":"148ED697","chunk_id":"cvb0drqsiim4e","chunk_label":"unnamed-chunk-40"},{"row":675,"row_count":1,"visible":true,"expansion_state":0,"options":{"engine":"r","label":"unnamed-chunk-300"},"document_id":"148ED697","chunk_id":"cxh6th20pwme8","chunk_label":"unnamed-chunk-41"},{"row":684,"row_count":1,"visible":true,"expansion_state":0,"options":{"engine":"r","label":"unnamed-chunk-11"},"document_id":"148ED697","chunk_id":"cafpogxj8fs8b","chunk_label":"unnamed-chunk-42"},{"row":691,"row_count":1,"visible":true,"expansion_state":0,"options":{"engine":"r","label":"unnamed-chunk-12"},"document_id":"148ED697","chunk_id":"ctmxc2igc8rqj","chunk_label":"unnamed-chunk-43"},{"row":697,"row_count":1,"visible":true,"expansion_state":0,"options":{"engine":"r","label":"unnamed-chunk-164"},"document_id":"148ED697","chunk_id":"cg3r0es564hdc","chunk_label":"unnamed-chunk-44"},{"row":742,"row_count":1,"visible":true,"expansion_state":0,"options":{"engine":"r","label":"unnamed-chunk-14"},"document_id":"148ED697","chunk_id":"cwy2t99y3bxkf","chunk_label":"unnamed-chunk-45"}],"doc_write_time":1684912123,"working_dir":null,"default_chunk_options":{"echo":true},"chunk_rendered_width":583}